Metadata-Version: 2.1
Name: testflows.combinatorics
Version: 1.1.230719.1184419
Summary: TestFlows - Combinatorics
Home-page: https://github.com/testflows/testflows-combinatorics
Author: Vitaliy Zakaznikov
Author-email: vzakaznikov@testflows.com
License: Apache-2.0
Classifier: Development Status :: 4 - Beta
Classifier: Programming Language :: Python :: 3
Classifier: License :: OSI Approved :: Apache Software License
Classifier: Operating System :: POSIX :: Linux
Requires-Python: >=3.6
Provides-Extra: dev
License-File: LICENSE
